loggingA/__init__.py
loggingA/logger.py
loggingA-0.0.7.dist-info/LICENSE
loggingA-0.0.7.dist-info/METADATA
loggingA-0.0.7.dist-info/WHEEL
loggingA-0.0.7.dist-info/top_level.txt
loggingA-0.0.7.dist-info/RECORD
