Metadata-Version: 2.1
Name: loggingA
Version: 0.0.7
Summary: 自定义日志模块
Home-page: https://github.com/al6nlee/loggingA
Author: alan
Author-email: al6nlee@gmail.com
License: MIT
Classifier: Intended Audience :: Developers
Classifier: License :: OSI Approved :: MIT License
Classifier: Programming Language :: Python
Classifier: Programming Language :: Python :: 3.8
Classifier: Programming Language :: Python :: 3.9
Classifier: Programming Language :: Python :: 3.10
Classifier: Programming Language :: Python :: 3.11
Classifier: Topic :: Software Development
Requires-Python: >=3.8
License-File: LICENSE
